{
    "tafasir": {
      "name": "الخلاصة من تفسير الطبري",
      "soar": [
        {
          "id": 9,
          "tafsir_id": 1,
          "name": "سورة الفاتحة كاملة",
          "url": "https://server17.mp3quran.net/tafseer/tabri/001.mp3",
          "sura_id": 1
        },
        {
          "id": 10,
          "tafsir_id": 1,
          "name": "سورة البقرة الايات من 1 الى 25",
          "url": "https://server17.mp3quran.net/tafseer/tabri/002-1-25.mp3",
          "sura_id": 2
        },
        {
          "id": 11,
          "tafsir_id": 1,
          "name": "سورة البقرة الايات من 26 الى 43",
          "url": "https://server17.mp3quran.net/tafseer/tabri/002-26-43.mp3",
          "sura_id": 2
        },
        {
          "id": 13,
          "tafsir_id": 1,
          "name": "سورة البقرة الايات من 44 الى 59",
          "url": "https://server17.mp3quran.net/tafseer/tabri/002-44-59.mp3",
          "sura_id": 2
        },
        {
          "id": 14,
          "tafsir_id": 1,
          "name": "سورة البقرة الايات من 60 الى 74",
          "url": "https://server17.mp3quran.net/tafseer/tabri/002-60-74.mp3",
          "sura_id": 2
        },
        {
          "id": 15,
          "tafsir_id": 1,
          "name": "سورة البقرة الايات من 75 الى 91",
          "url": "https://server17.mp3quran.net/tafseer/tabri/002-75-91.mp3",
          "sura_id": 2
        },
        {
          "id": 16,
          "tafsir_id": 1,
          "name": "سورة البقرة الايات من 92 الى 105",
          "url": "https://server17.mp3quran.net/tafseer/tabri/002-92-105.mp3",
          "sura_id": 2
        },
        {
          "id": 17,
          "tafsir_id": 1,
          "name": "سورة البقرة الايات من 106 الى 123",
          "url": "https://server17.mp3quran.net/tafseer/tabri/002-106-123.mp3",
          "sura_id": 2
        },
        {
          "id": 18,
          "tafsir_id": 1,
          "name": "سورة البقرة الايات من 124 الى 141",
          "url": "https://server17.mp3quran.net/tafseer/tabri/002-124-141.mp3",
          "sura_id": 2
        },
        {
          "id": 19,
          "tafsir_id": 1,
          "name": "سورة البقرة الايات من 142 الى 157",
          "url": "https://server17.mp3quran.net/tafseer/tabri/002-142-157.mp3",
          "sura_id": 2
        },
        {
          "id": 20,
          "tafsir_id": 1,
          "name": "سورة البقرة الايات من 158 الى 176",
          "url": "https://server17.mp3quran.net/tafseer/tabri/002-158-176.mp3",
          "sura_id": 2
        },
        {
          "id": 21,
          "tafsir_id": 1,
          "name": "سورة البقرة الايات من 177 الى 188",
          "url": "https://server17.mp3quran.net/tafseer/tabri/002-177-188.mp3",
          "sura_id": 2
        },
        {
          "id": 22,
          "tafsir_id": 1,
          "name": "سورة البقرة الايات من 189 الى 202",
          "url": "https://server17.mp3quran.net/tafseer/tabri/002-189-202.mp3",
          "sura_id": 2
        },
        {
          "id": 23,
          "tafsir_id": 1,
          "name": "سورة البقرة الايات من 203 الى 218",
          "url": "https://server17.mp3quran.net/tafseer/tabri/002-203-218.mp3",
          "sura_id": 2
        },
        {
          "id": 24,
          "tafsir_id": 1,
          "name": "سورة البقرة الايات من 219 الى 232",
          "url": "https://server17.mp3quran.net/tafseer/tabri/002-219-232.mp3",
          "sura_id": 2
        },
        {
          "id": 25,
          "tafsir_id": 1,
          "name": "سورة البقرة الايات من 233 الى 242",
          "url": "https://server17.mp3quran.net/tafseer/tabri/002-233-242.mp3",
          "sura_id": 2
        },
        {
          "id": 26,
          "tafsir_id": 1,
          "name": "سورة البقرة الايات من 243 الى 252",
          "url": "https://server17.mp3quran.net/tafseer/tabri/002-243-252.mp3",
          "sura_id": 2
        },
        {
          "id": 27,
          "tafsir_id": 1,
          "name": "سورة البقرة الايات من 253 الى 262",
          "url": "https://server17.mp3quran.net/tafseer/tabri/002-253-262.mp3",
          "sura_id": 2
        },
        {
          "id": 28,
          "tafsir_id": 1,
          "name": "سورة البقرة الايات من 263 الى 271",
          "url": "https://server17.mp3quran.net/tafseer/tabri/002-263-271.mp3",
          "sura_id": 2
        },
        {
          "id": 29,
          "tafsir_id": 1,
          "name": "سورة البقرة الايات من 272 الى 282",
          "url": "https://server17.mp3quran.net/tafseer/tabri/002-272-282.mp3",
          "sura_id": 2
        },
        {
          "id": 30,
          "tafsir_id": 1,
          "name": "سورة البقرة الايات من 283 الى 286",
          "url": "https://server17.mp3quran.net/tafseer/tabri/002-283-286.mp3",
          "sura_id": 2
        },
        {
          "id": 31,
          "tafsir_id": 1,
          "name": "سورة آل عمران الايات من 1 الى 14",
          "url": "https://server17.mp3quran.net/tafseer/tabri/003-1-14.mp3",
          "sura_id": 3
        },
        {
          "id": 32,
          "tafsir_id": 1,
          "name": "سورة آل عمران الايات من 15 الى 32",
          "url": "https://server17.mp3quran.net/tafseer/tabri/003-15-32.mp3",
          "sura_id": 3
        },
        {
          "id": 33,
          "tafsir_id": 1,
          "name": "سورة آل عمران الايات من 33 الى 51",
          "url": "https://server17.mp3quran.net/tafseer/tabri/003-33-51.mp3",
          "sura_id": 3
        },
        {
          "id": 34,
          "tafsir_id": 1,
          "name": "سورة آل عمران الايات من 52 الى 74",
          "url": "https://server17.mp3quran.net/tafseer/tabri/003-52-74.mp3",
          "sura_id": 3
        },
        {
          "id": 35,
          "tafsir_id": 1,
          "name": "سورة آل عمران الايات من 75 الى 92",
          "url": "https://server17.mp3quran.net/tafseer/tabri/003-75-92.mp3",
          "sura_id": 3
        },
        {
          "id": 36,
          "tafsir_id": 1,
          "name": "سورة آل عمران الايات من 93 الى 112",
          "url": "https://server17.mp3quran.net/tafseer/tabri/003-93-112.mp3",
          "sura_id": 3
        },
        {
          "id": 37,
          "tafsir_id": 1,
          "name": "سورة آل عمران الايات من 113 الى 132",
          "url": "https://server17.mp3quran.net/tafseer/tabri/003-113-132.mp3",
          "sura_id": 3
        },
        {
          "id": 38,
          "tafsir_id": 1,
          "name": "سورة آل عمران الايات من 133 الى 152",
          "url": "https://server17.mp3quran.net/tafseer/tabri/003-133-152.mp3",
          "sura_id": 3
        },
        {
          "id": 39,
          "tafsir_id": 1,
          "name": "سورة آل عمران الايات من 153 الى 171",
          "url": "https://server17.mp3quran.net/tafseer/tabri/003-153-171.mp3",
          "sura_id": 3
        },
        {
          "id": 40,
          "tafsir_id": 1,
          "name": "سورة آل عمران الايات من 172 الى 185",
          "url": "https://server17.mp3quran.net/tafseer/tabri/003-172-185.mp3",
          "sura_id": 3
        },
        {
          "id": 41,
          "tafsir_id": 1,
          "name": "سورة آل عمران الايات من 186 الى 200",
          "url": "https://server17.mp3quran.net/tafseer/tabri/003-186-200.mp3",
          "sura_id": 3
        },
        {
          "id": 42,
          "tafsir_id": 1,
          "name": "سورة النساء الايات من 1 الى 11",
          "url": "https://server17.mp3quran.net/tafseer/tabri/004-1-11.mp3",
          "sura_id": 4
        },
        {
          "id": 43,
          "tafsir_id": 1,
          "name": "سورة النساء الايات من 12 الى 23",
          "url": "https://server17.mp3quran.net/tafseer/tabri/004-12-23.mp3",
          "sura_id": 4
        },
        {
          "id": 44,
          "tafsir_id": 1,
          "name": "سورة النساء الايات من 24 الى 35",
          "url": "https://server17.mp3quran.net/tafseer/tabri/004-24-35.mp3",
          "sura_id": 4
        },
        {
          "id": 45,
          "tafsir_id": 1,
          "name": "سورة النساء الايات من 36 الى 57",
          "url": "https://server17.mp3quran.net/tafseer/tabri/004-36-57.mp3",
          "sura_id": 4
        },
        {
          "id": 46,
          "tafsir_id": 1,
          "name": "سورة النساء الايات من 58 الى 73",
          "url": "https://server17.mp3quran.net/tafseer/tabri/004-58-73.mp3",
          "sura_id": 4
        },
        {
          "id": 47,
          "tafsir_id": 1,
          "name": "سورة النساء الايات من 74 الى 87",
          "url": "https://server17.mp3quran.net/tafseer/tabri/004-74-87.mp3",
          "sura_id": 4
        },
        {
          "id": 48,
          "tafsir_id": 1,
          "name": "سورة النساء الايات من 88 الى 99",
          "url": "https://server17.mp3quran.net/tafseer/tabri/004-88-99.mp3",
          "sura_id": 4
        },
        {
          "id": 49,
          "tafsir_id": 1,
          "name": "سورة النساء الايات من 100 الى 113",
          "url": "https://server17.mp3quran.net/tafseer/tabri/004-100-113.mp3",
          "sura_id": 4
        },
        {
          "id": 50,
          "tafsir_id": 1,
          "name": "سورة النساء الايات من 114 الى 134",
          "url": "https://server17.mp3quran.net/tafseer/tabri/004-114-134.mp3",
          "sura_id": 4
        },
        {
          "id": 51,
          "tafsir_id": 1,
          "name": "سورة النساء الايات من 135 الى 147",
          "url": "https://server17.mp3quran.net/tafseer/tabri/004-135-147.mp3",
          "sura_id": 4
        },
        {
          "id": 52,
          "tafsir_id": 1,
          "name": "سورة النساء الايات من 148 الى 162",
          "url": "https://server17.mp3quran.net/tafseer/tabri/004-148-162.mp3",
          "sura_id": 4
        },
        {
          "id": 53,
          "tafsir_id": 1,
          "name": "سورة النساء الايات من 163 الى 176",
          "url": "https://server17.mp3quran.net/tafseer/tabri/004-163-176.mp3",
          "sura_id": 4
        },
        {
          "id": 54,
          "tafsir_id": 1,
          "name": "سورة المائدة الايات من 1 الى 11",
          "url": "https://server17.mp3quran.net/tafseer/tabri/005-1-11.mp3",
          "sura_id": 5
        },
        {
          "id": 55,
          "tafsir_id": 1,
          "name": "سورة المائدة الايات من 12 الى 26",
          "url": "https://server17.mp3quran.net/tafseer/tabri/005-12-26.mp3",
          "sura_id": 5
        },
        {
          "id": 56,
          "tafsir_id": 1,
          "name": "سورة المائدة الايات من 27 الى 40",
          "url": "https://server17.mp3quran.net/tafseer/tabri/005-27-40.mp3",
          "sura_id": 5
        },
        {
          "id": 57,
          "tafsir_id": 1,
          "name": "سورة المائدة الايات من 41 الى 50",
          "url": "https://server17.mp3quran.net/tafseer/tabri/005-41-50.mp3",
          "sura_id": 5
        },
        {
          "id": 58,
          "tafsir_id": 1,
          "name": "سورة المائدة الايات من 51 الى 66",
          "url": "https://server17.mp3quran.net/tafseer/tabri/005-51-66.mp3",
          "sura_id": 5
        },
        {
          "id": 59,
          "tafsir_id": 1,
          "name": "سورة المائدة الايات من 67 الى 81",
          "url": "https://server17.mp3quran.net/tafseer/tabri/005-67-81.mp3",
          "sura_id": 5
        },
        {
          "id": 60,
          "tafsir_id": 1,
          "name": "سورة المائدة الايات من 82 الى 96",
          "url": "https://server17.mp3quran.net/tafseer/tabri/005-82-96.mp3",
          "sura_id": 5
        },
        {
          "id": 61,
          "tafsir_id": 1,
          "name": "سورة المائدة الايات من 97 الى 108",
          "url": "https://server17.mp3quran.net/tafseer/tabri/005-97-108.mp3",
          "sura_id": 5
        },
        {
          "id": 62,
          "tafsir_id": 1,
          "name": "سورة المائدة الايات من 109 الى 120",
          "url": "https://server17.mp3quran.net/tafseer/tabri/005-109-120.mp3",
          "sura_id": 5
        },
        {
          "id": 63,
          "tafsir_id": 1,
          "name": "سورة الأنعام الايات من 1 الى 12",
          "url": "https://server17.mp3quran.net/tafseer/tabri/006-1-12.mp3",
          "sura_id": 6
        },
        {
          "id": 64,
          "tafsir_id": 1,
          "name": "سورة الأنعام الايات من 13 الى 35",
          "url": "https://server17.mp3quran.net/tafseer/tabri/006-13-35.mp3",
          "sura_id": 6
        },
        {
          "id": 65,
          "tafsir_id": 1,
          "name": "سورة الأنعام الايات من 36 الى 58",
          "url": "https://server17.mp3quran.net/tafseer/tabri/006-36-58.mp3",
          "sura_id": 6
        },
        {
          "id": 66,
          "tafsir_id": 1,
          "name": "سورة الأنعام الايات من 59 الى 73",
          "url": "https://server17.mp3quran.net/tafseer/tabri/006-59-73.mp3",
          "sura_id": 6
        },
        {
          "id": 67,
          "tafsir_id": 1,
          "name": "سورة الأنعام الايات من 74 الى 94",
          "url": "https://server17.mp3quran.net/tafseer/tabri/006-74-94.mp3",
          "sura_id": 6
        },
        {
          "id": 68,
          "tafsir_id": 1,
          "name": "سورة الأنعام الايات من 95 الى 110",
          "url": "https://server17.mp3quran.net/tafseer/tabri/006-95-110.mp3",
          "sura_id": 6
        },
        {
          "id": 69,
          "tafsir_id": 1,
          "name": "سورة الأنعام الايات من 111 الى 126",
          "url": "https://server17.mp3quran.net/tafseer/tabri/006-111-126.mp3",
          "sura_id": 6
        },
        {
          "id": 70,
          "tafsir_id": 1,
          "name": "سورة الأنعام الايات من 127 الى 140",
          "url": "https://server17.mp3quran.net/tafseer/tabri/006-127-140.mp3",
          "sura_id": 6
        },
        {
          "id": 71,
          "tafsir_id": 1,
          "name": "سورة الأنعام الايات من 141 الى 150",
          "url": "https://server17.mp3quran.net/tafseer/tabri/006-141-150.mp3",
          "sura_id": 6
        },
        {
          "id": 72,
          "tafsir_id": 1,
          "name": "سورة الأنعام الايات من 151 الى 165",
          "url": "https://server17.mp3quran.net/tafseer/tabri/006-151-165.mp3",
          "sura_id": 6
        },
        {
          "id": 73,
          "tafsir_id": 1,
          "name": "سورة الأعراف الايات من 1 الى 30",
          "url": "https://server17.mp3quran.net/tafseer/tabri/007-1-30.mp3",
          "sura_id": 7
        },
        {
          "id": 74,
          "tafsir_id": 1,
          "name": "سورة الأعراف الايات من 31 الى 46",
          "url": "https://server17.mp3quran.net/tafseer/tabri/007-31-46.mp3",
          "sura_id": 7
        },
        {
          "id": 75,
          "tafsir_id": 1,
          "name": "سورة الأعراف الايات من 47 الى 64",
          "url": "https://server17.mp3quran.net/tafseer/tabri/007-47-64.mp3",
          "sura_id": 7
        },
        {
          "id": 76,
          "tafsir_id": 1,
          "name": "سورة الأعراف الايات من 65 الى 87",
          "url": "https://server17.mp3quran.net/tafseer/tabri/007-65-87.mp3",
          "sura_id": 7
        },
        {
          "id": 77,
          "tafsir_id": 1,
          "name": "سورة الأعراف الايات من 88 الى 116",
          "url": "https://server17.mp3quran.net/tafseer/tabri/007-88-116.mp3",
          "sura_id": 7
        },
        {
          "id": 78,
          "tafsir_id": 1,
          "name": "سورة الأعراف الايات من 117 الى 141",
          "url": "https://server17.mp3quran.net/tafseer/tabri/007-117-141.mp3",
          "sura_id": 7
        },
        {
          "id": 79,
          "tafsir_id": 1,
          "name": "سورة الأعراف الايات من 142 الى 155",
          "url": "https://server17.mp3quran.net/tafseer/tabri/007-142-155.mp3",
          "sura_id": 7
        },
        {
          "id": 80,
          "tafsir_id": 1,
          "name": "سورة الأعراف الايات من 156 الى 170",
          "url": "https://server17.mp3quran.net/tafseer/tabri/007-156-170.mp3",
          "sura_id": 7
        },
        {
          "id": 81,
          "tafsir_id": 1,
          "name": "سورة الأعراف الايات من 171 الى 188",
          "url": "https://server17.mp3quran.net/tafseer/tabri/007-171-188.mp3",
          "sura_id": 7
        },
        {
          "id": 82,
          "tafsir_id": 1,
          "name": "سورة الأعراف الايات من 189 الى 206",
          "url": "https://server17.mp3quran.net/tafseer/tabri/007-189-206.mp3",
          "sura_id": 7
        },
        {
          "id": 83,
          "tafsir_id": 1,
          "name": "سورة الأنفال الايات من 1 الى 21",
          "url": "https://server17.mp3quran.net/tafseer/tabri/008-1-21.mp3",
          "sura_id": 8
        },
        {
          "id": 84,
          "tafsir_id": 1,
          "name": "سورة الأنفال الايات من 22 الى 40",
          "url": "https://server17.mp3quran.net/tafseer/tabri/008-22-40.mp3",
          "sura_id": 8
        },
        {
          "id": 85,
          "tafsir_id": 1,
          "name": "سورة الأنفال الايات من 41 الى 60",
          "url": "https://server17.mp3quran.net/tafseer/tabri/008-41-60.mp3",
          "sura_id": 8
        },
        {
          "id": 86,
          "tafsir_id": 1,
          "name": "سورة الأنفال الايات من 61 الى 75",
          "url": "https://server17.mp3quran.net/tafseer/tabri/008-61-75.mp3",
          "sura_id": 8
        },
        {
          "id": 87,
          "tafsir_id": 1,
          "name": "سورة التوبة الايات من 1 الى 18",
          "url": "https://server17.mp3quran.net/tafseer/tabri/009-1-18.mp3",
          "sura_id": 9
        },
        {
          "id": 88,
          "tafsir_id": 1,
          "name": "سورة التوبة الايات من 19 الى 33",
          "url": "https://server17.mp3quran.net/tafseer/tabri/009-19-33.mp3",
          "sura_id": 9
        },
        {
          "id": 89,
          "tafsir_id": 1,
          "name": "سورة التوبة الايات من 34 الى 45",
          "url": "https://server17.mp3quran.net/tafseer/tabri/009-34-45.mp3",
          "sura_id": 9
        },
        {
          "id": 90,
          "tafsir_id": 1,
          "name": "سورة التوبة الايات من 46 الى 59",
          "url": "https://server17.mp3quran.net/tafseer/tabri/009-46-59.mp3",
          "sura_id": 9
        },
        {
          "id": 91,
          "tafsir_id": 1,
          "name": "سورة التوبة الايات من 60 الى 74",
          "url": "https://server17.mp3quran.net/tafseer/tabri/009-60-74.mp3",
          "sura_id": 9
        },
        {
          "id": 92,
          "tafsir_id": 1,
          "name": "سورة التوبة الايات من 75 الى 92",
          "url": "https://server17.mp3quran.net/tafseer/tabri/009-75-92.mp3",
          "sura_id": 9
        },
        {
          "id": 93,
          "tafsir_id": 1,
          "name": "سورة التوبة الايات من 93 الى 110",
          "url": "https://server17.mp3quran.net/tafseer/tabri/009-93-110.mp3",
          "sura_id": 9
        },
        {
          "id": 94,
          "tafsir_id": 1,
          "name": "سورة التوبة الايات من 111 الى 121",
          "url": "https://server17.mp3quran.net/tafseer/tabri/009-111-121.mp3",
          "sura_id": 9
        },
        {
          "id": 95,
          "tafsir_id": 1,
          "name": "سورة التوبة الايات من 122 الى 129",
          "url": "https://server17.mp3quran.net/tafseer/tabri/009-122-129.mp3",
          "sura_id": 9
        },
        {
          "id": 96,
          "tafsir_id": 1,
          "name": "سورة يونس الايات من 1 الى 10",
          "url": "https://server17.mp3quran.net/tafseer/tabri/010-1-10.mp3",
          "sura_id": 10
        },
        {
          "id": 97,
          "tafsir_id": 1,
          "name": "سورة يونس الايات من 11 الى 25",
          "url": "https://server17.mp3quran.net/tafseer/tabri/010-11-25.mp3",
          "sura_id": 10
        },
        {
          "id": 98,
          "tafsir_id": 1,
          "name": "سورة يونس الايات من 26 الى 52",
          "url": "https://server17.mp3quran.net/tafseer/tabri/010-26-52.mp3",
          "sura_id": 10
        },
        {
          "id": 99,
          "tafsir_id": 1,
          "name": "سورة يونس الايات من 53 الى 70",
          "url": "https://server17.mp3quran.net/tafseer/tabri/010-53-70.mp3",
          "sura_id": 10
        },
        {
          "id": 100,
          "tafsir_id": 1,
          "name": "سورة يونس الايات من 71 الى 89",
          "url": "https://server17.mp3quran.net/tafseer/tabri/010-71-89.mp3",
          "sura_id": 10
        },
        {
          "id": 101,
          "tafsir_id": 1,
          "name": "سورة يونس الايات من 90 الى 109",
          "url": "https://server17.mp3quran.net/tafseer/tabri/010-90-109.mp3",
          "sura_id": 10
        },
        {
          "id": 102,
          "tafsir_id": 1,
          "name": "سورة هود الايات من 1 الى 5",
          "url": "https://server17.mp3quran.net/tafseer/tabri/011-1-5.mp3",
          "sura_id": 11
        },
        {
          "id": 103,
          "tafsir_id": 1,
          "name": "سورة هود الايات من 6 الى 23",
          "url": "https://server17.mp3quran.net/tafseer/tabri/011-6-23.mp3",
          "sura_id": 11
        },
        {
          "id": 104,
          "tafsir_id": 1,
          "name": "سورة هود الايات من 24 الى 40",
          "url": "https://server17.mp3quran.net/tafseer/tabri/011-24-40.mp3",
          "sura_id": 11
        },
        {
          "id": 105,
          "tafsir_id": 1,
          "name": "سورة هود الايات من 41 الى 60",
          "url": "https://server17.mp3quran.net/tafseer/tabri/011-41-60.mp3",
          "sura_id": 11
        },
        {
          "id": 106,
          "tafsir_id": 1,
          "name": "سورة هود الايات من 61 الى 83",
          "url": "https://server17.mp3quran.net/tafseer/tabri/011-61-83.mp3",
          "sura_id": 11
        },
        {
          "id": 107,
          "tafsir_id": 1,
          "name": "سورة هود الايات من 84 الى 107",
          "url": "https://server17.mp3quran.net/tafseer/tabri/011-84-107.mp3",
          "sura_id": 11
        },
        {
          "id": 108,
          "tafsir_id": 1,
          "name": "سورة هود الايات من 108 الى 123",
          "url": "https://server17.mp3quran.net/tafseer/tabri/011-108-123.mp3",
          "sura_id": 11
        },
        {
          "id": 109,
          "tafsir_id": 1,
          "name": "سورة يوسف الايات من 1 الى 6",
          "url": "https://server17.mp3quran.net/tafseer/tabri/012-1-6.mp3",
          "sura_id": 12
        },
        {
          "id": 110,
          "tafsir_id": 1,
          "name": "سورة يوسف الايات من 7 الى 29",
          "url": "https://server17.mp3quran.net/tafseer/tabri/012-7-29.mp3",
          "sura_id": 12
        },
        {
          "id": 111,
          "tafsir_id": 1,
          "name": "سورة يوسف الايات من 30 الى 52",
          "url": "https://server17.mp3quran.net/tafseer/tabri/012-30-52.mp3",
          "sura_id": 12
        },
        {
          "id": 112,
          "tafsir_id": 1,
          "name": "سورة يوسف الايات من 53 الى 76",
          "url": "https://server17.mp3quran.net/tafseer/tabri/012-53-76.mp3",
          "sura_id": 12
        },
        {
          "id": 113,
          "tafsir_id": 1,
          "name": "سورة يوسف الايات من 77 الى 100",
          "url": "https://server17.mp3quran.net/tafseer/tabri/012-77-100.mp3",
          "sura_id": 12
        },
        {
          "id": 114,
          "tafsir_id": 1,
          "name": "سورة يوسف الايات من 101 الى 111",
          "url": "https://server17.mp3quran.net/tafseer/tabri/012-101-111.mp3",
          "sura_id": 12
        },
        {
          "id": 115,
          "tafsir_id": 1,
          "name": "سورة الرعد الايات من 1 الى 4",
          "url": "https://server17.mp3quran.net/tafseer/tabri/013-1-4.mp3",
          "sura_id": 13
        },
        {
          "id": 116,
          "tafsir_id": 1,
          "name": "سورة الرعد الايات من 5 الى 18",
          "url": "https://server17.mp3quran.net/tafseer/tabri/013-5-18.mp3",
          "sura_id": 13
        },
        {
          "id": 117,
          "tafsir_id": 1,
          "name": "سورة الرعد الايات من 19 الى 34",
          "url": "https://server17.mp3quran.net/tafseer/tabri/013-19-34.mp3",
          "sura_id": 13
        },
        {
          "id": 118,
          "tafsir_id": 1,
          "name": "سورة الرعد الايات من 35 الى 43",
          "url": "https://server17.mp3quran.net/tafseer/tabri/013-35-43.mp3",
          "sura_id": 13
        },
        {
          "id": 119,
          "tafsir_id": 1,
          "name": "سورة إبراهيم الايات من 1 الى 9",
          "url": "https://server17.mp3quran.net/tafseer/tabri/014-1-9.mp3",
          "sura_id": 14
        },
        {
          "id": 120,
          "tafsir_id": 1,
          "name": "سورة إبراهيم الايات من 10 الى 27",
          "url": "https://server17.mp3quran.net/tafseer/tabri/014-10-27.mp3",
          "sura_id": 14
        },
        {
          "id": 121,
          "tafsir_id": 1,
          "name": "سورة إبراهيم الايات من 28 الى 52",
          "url": "https://server17.mp3quran.net/tafseer/tabri/014-28-52.mp3",
          "sura_id": 14
        },
        {
          "id": 122,
          "tafsir_id": 1,
          "name": "سورة الحجر الايات من 1 الى 48",
          "url": "https://server17.mp3quran.net/tafseer/tabri/015-1-48.mp3",
          "sura_id": 15
        },
        {
          "id": 123,
          "tafsir_id": 1,
          "name": "سورة الحجر الايات من 49 الى 99",
          "url": "https://server17.mp3quran.net/tafseer/tabri/015-49-99.mp3",
          "sura_id": 15
        },
        {
          "id": 124,
          "tafsir_id": 1,
          "name": "سورة النحل الايات من 1 الى 29",
          "url": "https://server17.mp3quran.net/tafseer/tabri/016-1-29.mp3",
          "sura_id": 16
        },
        {
          "id": 125,
          "tafsir_id": 1,
          "name": "سورة النحل الايات من 30 الى 50",
          "url": "https://server17.mp3quran.net/tafseer/tabri/016-30-50.mp3",
          "sura_id": 16
        },
        {
          "id": 126,
          "tafsir_id": 1,
          "name": "سورة النحل الايات من 51 الى 74",
          "url": "https://server17.mp3quran.net/tafseer/tabri/016-51-74.mp3",
          "sura_id": 16
        },
        {
          "id": 127,
          "tafsir_id": 1,
          "name": "سورة النحل الايات من 90 الى 110",
          "url": "https://server17.mp3quran.net/tafseer/tabri/016-90-110.mp3",
          "sura_id": 16
        },
        {
          "id": 128,
          "tafsir_id": 1,
          "name": "سورة النحل الايات من 111 الى 128",
          "url": "https://server17.mp3quran.net/tafseer/tabri/016-111-128.mp3",
          "sura_id": 16
        },
        {
          "id": 129,
          "tafsir_id": 1,
          "name": "سورة الإسراء الايات من 1 الى 22",
          "url": "https://server17.mp3quran.net/tafseer/tabri/017-1-22.mp3",
          "sura_id": 17
        },
        {
          "id": 130,
          "tafsir_id": 1,
          "name": "سورة الإسراء الايات من 23 الى 49",
          "url": "https://server17.mp3quran.net/tafseer/tabri/017-23-49.mp3",
          "sura_id": 17
        },
        {
          "id": 131,
          "tafsir_id": 1,
          "name": "سورة الإسراء الايات من 50 الى 69",
          "url": "https://server17.mp3quran.net/tafseer/tabri/017-50-69.mp3",
          "sura_id": 17
        },
        {
          "id": 132,
          "tafsir_id": 1,
          "name": "سورة الإسراء الايات من 70 الى 98",
          "url": "https://server17.mp3quran.net/tafseer/tabri/017-70-98.mp3",
          "sura_id": 17
        },
        {
          "id": 133,
          "tafsir_id": 1,
          "name": "سورة الإسراء الايات من 99 الى 111",
          "url": "https://server17.mp3quran.net/tafseer/tabri/017-99-111.mp3",
          "sura_id": 17
        },
        {
          "id": 134,
          "tafsir_id": 1,
          "name": "سورة الكهف الايات من 1 الى 16",
          "url": "https://server17.mp3quran.net/tafseer/tabri/018-1-16.mp3",
          "sura_id": 18
        },
        {
          "id": 135,
          "tafsir_id": 1,
          "name": "سورة الكهف الايات من 17 الى 31",
          "url": "https://server17.mp3quran.net/tafseer/tabri/018-17-31.mp3",
          "sura_id": 18
        },
        {
          "id": 136,
          "tafsir_id": 1,
          "name": "سورة الكهف الايات من 32 الى 50",
          "url": "https://server17.mp3quran.net/tafseer/tabri/018-32-50.mp3",
          "sura_id": 18
        },
        {
          "id": 137,
          "tafsir_id": 1,
          "name": "سورة الكهف الايات من 51 الى 74",
          "url": "https://server17.mp3quran.net/tafseer/tabri/018-51-74.mp3",
          "sura_id": 18
        },
        {
          "id": 138,
          "tafsir_id": 1,
          "name": "سورة الكهف الايات من 75 الى 98",
          "url": "https://server17.mp3quran.net/tafseer/tabri/018-75-98.mp3",
          "sura_id": 18
        },
        {
          "id": 139,
          "tafsir_id": 1,
          "name": "سورة الكهف الايات من 99 الى 110",
          "url": "https://server17.mp3quran.net/tafseer/tabri/018-99-110.mp3",
          "sura_id": 18
        },
        {
          "id": 140,
          "tafsir_id": 1,
          "name": "سورة مريم الايات من 1 الى 21",
          "url": "https://server17.mp3quran.net/tafseer/tabri/019-1-21.mp3",
          "sura_id": 19
        },
        {
          "id": 141,
          "tafsir_id": 1,
          "name": "سورة مريم الايات من 22 الى 58",
          "url": "https://server17.mp3quran.net/tafseer/tabri/019-22-58.mp3",
          "sura_id": 19
        },
        {
          "id": 142,
          "tafsir_id": 1,
          "name": "سورة مريم الايات من 59 الى 98",
          "url": "https://server17.mp3quran.net/tafseer/tabri/019-59-98.mp3",
          "sura_id": 19
        },
        {
          "id": 143,
          "tafsir_id": 1,
          "name": "سورة طه الايات من 1 الى 54",
          "url": "https://server17.mp3quran.net/tafseer/tabri/020-1-54.mp3",
          "sura_id": 20
        },
        {
          "id": 144,
          "tafsir_id": 1,
          "name": "سورة طه الايات من 55 الى 82",
          "url": "https://server17.mp3quran.net/tafseer/tabri/020-55-82.mp3",
          "sura_id": 20
        },
        {
          "id": 145,
          "tafsir_id": 1,
          "name": "سورة طه الايات من 83 الى 110",
          "url": "https://server17.mp3quran.net/tafseer/tabri/020-83-110.mp3",
          "sura_id": 20
        },
        {
          "id": 146,
          "tafsir_id": 1,
          "name": "سورة طه الايات من 111 الى 135",
          "url": "https://server17.mp3quran.net/tafseer/tabri/020-111-135.mp3",
          "sura_id": 20
        },
        {
          "id": 147,
          "tafsir_id": 1,
          "name": "سورة الأنبياء الايات من 1 الى 28",
          "url": "https://server17.mp3quran.net/tafseer/tabri/021-1-28.mp3",
          "sura_id": 21
        },
        {
          "id": 148,
          "tafsir_id": 1,
          "name": "سورة الأنبياء الايات من 29 الى 50",
          "url": "https://server17.mp3quran.net/tafseer/tabri/021-29-50.mp3",
          "sura_id": 21
        },
        {
          "id": 149,
          "tafsir_id": 1,
          "name": "سورة الأنبياء الايات من 51 الى 82",
          "url": "https://server17.mp3quran.net/tafseer/tabri/021-51-82.mp3",
          "sura_id": 21
        },
        {
          "id": 150,
          "tafsir_id": 1,
          "name": "سورة الأنبياء الايات من 83 الى 112",
          "url": "https://server17.mp3quran.net/tafseer/tabri/021-83-112.mp3",
          "sura_id": 21
        },
        {
          "id": 151,
          "tafsir_id": 1,
          "name": "سورة الحج الايات من 1 الى 18",
          "url": "https://server17.mp3quran.net/tafseer/tabri/022-1-18.mp3",
          "sura_id": 22
        },
        {
          "id": 152,
          "tafsir_id": 1,
          "name": "سورة الحج الايات من 19 الى 37",
          "url": "https://server17.mp3quran.net/tafseer/tabri/022-19-37.mp3",
          "sura_id": 22
        },
        {
          "id": 153,
          "tafsir_id": 1,
          "name": "سورة الحج الايات من 38 الى 59",
          "url": "https://server17.mp3quran.net/tafseer/tabri/022-38-59.mp3",
          "sura_id": 22
        },
        {
          "id": 154,
          "tafsir_id": 1,
          "name": "سورة الحج الايات من 60 الى 78",
          "url": "https://server17.mp3quran.net/tafseer/tabri/022-60-78.mp3",
          "sura_id": 22
        },
        {
          "id": 155,
          "tafsir_id": 1,
          "name": "سورة المؤمنون الايات من 1 الى 35",
          "url": "https://server17.mp3quran.net/tafseer/tabri/023-1-35.mp3",
          "sura_id": 23
        },
        {
          "id": 156,
          "tafsir_id": 1,
          "name": "سورة المؤمنون الايات من 36 الى 74",
          "url": "https://server17.mp3quran.net/tafseer/tabri/023-36-74.mp3",
          "sura_id": 23
        },
        {
          "id": 157,
          "tafsir_id": 1,
          "name": "سورة المؤمنون الايات من 75 الى 118",
          "url": "https://server17.mp3quran.net/tafseer/tabri/023-75-118.mp3",
          "sura_id": 23
        },
        {
          "id": 158,
          "tafsir_id": 1,
          "name": "سورة النور الايات من 1 الى 20",
          "url": "https://server17.mp3quran.net/tafseer/tabri/024-1-20.mp3",
          "sura_id": 24
        },
        {
          "id": 159,
          "tafsir_id": 1,
          "name": "سورة النور الايات من 21 الى 34",
          "url": "https://server17.mp3quran.net/tafseer/tabri/024-21-34.mp3",
          "sura_id": 24
        },
        {
          "id": 160,
          "tafsir_id": 1,
          "name": "سورة النور الايات من 35 الى 52",
          "url": "https://server17.mp3quran.net/tafseer/tabri/024-35-52.mp3",
          "sura_id": 24
        },
        {
          "id": 161,
          "tafsir_id": 1,
          "name": "سورة النور الايات من 53 الى 64",
          "url": "https://server17.mp3quran.net/tafseer/tabri/024-53-64.mp3",
          "sura_id": 24
        },
        {
          "id": 162,
          "tafsir_id": 1,
          "name": "سورة الفرقان الايات من 1 الى 20",
          "url": "https://server17.mp3quran.net/tafseer/tabri/025-1-20.mp3",
          "sura_id": 25
        },
        {
          "id": 163,
          "tafsir_id": 1,
          "name": "سورة الفرقان الايات من 21 الى 52",
          "url": "https://server17.mp3quran.net/tafseer/tabri/025-21-52.mp3",
          "sura_id": 25
        },
        {
          "id": 164,
          "tafsir_id": 1,
          "name": "سورة الفرقان الايات من 53 الى 77",
          "url": "https://server17.mp3quran.net/tafseer/tabri/025-53-77.mp3",
          "sura_id": 25
        },
        {
          "id": 165,
          "tafsir_id": 1,
          "name": "سورة الشعراء الايات من 1 الى 51",
          "url": "https://server17.mp3quran.net/tafseer/tabri/026-1-51.mp3",
          "sura_id": 26
        },
        {
          "id": 166,
          "tafsir_id": 1,
          "name": "سورة الشعراء الايات من 52 الى 110",
          "url": "https://server17.mp3quran.net/tafseer/tabri/026-52-110.mp3",
          "sura_id": 26
        },
        {
          "id": 167,
          "tafsir_id": 1,
          "name": "سورة الشعراء الايات من 111 الى 180",
          "url": "https://server17.mp3quran.net/tafseer/tabri/026-111-180.mp3",
          "sura_id": 26
        },
        {
          "id": 168,
          "tafsir_id": 1,
          "name": "سورة الشعراء الايات من 181 الى 227",
          "url": "https://server17.mp3quran.net/tafseer/tabri/026-181-227.mp3",
          "sura_id": 26
        },
        {
          "id": 169,
          "tafsir_id": 1,
          "name": "سورة النمل الايات من 1 الى 26",
          "url": "https://server17.mp3quran.net/tafseer/tabri/027-1-26.mp3",
          "sura_id": 27
        },
        {
          "id": 170,
          "tafsir_id": 1,
          "name": "سورة النمل الايات من 27 الى 55",
          "url": "https://server17.mp3quran.net/tafseer/tabri/027-27-55.mp3",
          "sura_id": 27
        },
        {
          "id": 171,
          "tafsir_id": 1,
          "name": "سورة النمل الايات من 56 الى 81",
          "url": "https://server17.mp3quran.net/tafseer/tabri/027-56-81.mp3",
          "sura_id": 27
        },
        {
          "id": 172,
          "tafsir_id": 1,
          "name": "سورة النمل الايات من 82 الى 93",
          "url": "https://server17.mp3quran.net/tafseer/tabri/027-82-93.mp3",
          "sura_id": 27
        },
        {
          "id": 173,
          "tafsir_id": 1,
          "name": "سورة القصص الايات من 1 الى 11",
          "url": "https://server17.mp3quran.net/tafseer/tabri/028-1-11.mp3",
          "sura_id": 28
        },
        {
          "id": 174,
          "tafsir_id": 1,
          "name": "سورة القصص الايات من 12 الى 28",
          "url": "https://server17.mp3quran.net/tafseer/tabri/028-12-28.mp3",
          "sura_id": 28
        },
        {
          "id": 175,
          "tafsir_id": 1,
          "name": "سورة القصص الايات من 29 الى 50",
          "url": "https://server17.mp3quran.net/tafseer/tabri/028-29-50.mp3",
          "sura_id": 28
        },
        {
          "id": 176,
          "tafsir_id": 1,
          "name": "سورة القصص الايات من 51 الى 75",
          "url": "https://server17.mp3quran.net/tafseer/tabri/028-51-75.mp3",
          "sura_id": 28
        },
        {
          "id": 177,
          "tafsir_id": 1,
          "name": "سورة القصص الايات من 76 الى 88",
          "url": "https://server17.mp3quran.net/tafseer/tabri/028-76-88.mp3",
          "sura_id": 28
        },
        {
          "id": 178,
          "tafsir_id": 1,
          "name": "سورة العنكبوت الايات من 1 الى 25",
          "url": "https://server17.mp3quran.net/tafseer/tabri/029-1-25.mp3",
          "sura_id": 29
        },
        {
          "id": 179,
          "tafsir_id": 1,
          "name": "سورة العنكبوت الايات من 26 الى 45",
          "url": "https://server17.mp3quran.net/tafseer/tabri/029-26-45.mp3",
          "sura_id": 29
        },
        {
          "id": 180,
          "tafsir_id": 1,
          "name": "سورة العنكبوت الايات من 46 الى 69",
          "url": "https://server17.mp3quran.net/tafseer/tabri/029-46-69.mp3",
          "sura_id": 29
        },
        {
          "id": 181,
          "tafsir_id": 1,
          "name": "سورة الروم الايات من 1 الى 30",
          "url": "https://server17.mp3quran.net/tafseer/tabri/030-1-30.mp3",
          "sura_id": 30
        },
        {
          "id": 182,
          "tafsir_id": 1,
          "name": "سورة الروم الايات من 31 الى 53",
          "url": "https://server17.mp3quran.net/tafseer/tabri/030-31-53.mp3",
          "sura_id": 30
        },
        {
          "id": 183,
          "tafsir_id": 1,
          "name": "سورة الروم الايات من 54 الى 60",
          "url": "https://server17.mp3quran.net/tafseer/tabri/030-54-60.mp3",
          "sura_id": 30
        },
        {
          "id": 184,
          "tafsir_id": 1,
          "name": "سورة لقمان الايات من 1 الى 21",
          "url": "https://server17.mp3quran.net/tafseer/tabri/031-1-21.mp3",
          "sura_id": 31
        },
        {
          "id": 185,
          "tafsir_id": 1,
          "name": "سورة لقمان الايات من 22 الى 34",
          "url": "https://server17.mp3quran.net/tafseer/tabri/031-22-34.mp3",
          "sura_id": 31
        },
        {
          "id": 186,
          "tafsir_id": 1,
          "name": "سورة السجدة الايات من 1 الى 10",
          "url": "https://server17.mp3quran.net/tafseer/tabri/032-1-10.mp3",
          "sura_id": 32
        },
        {
          "id": 187,
          "tafsir_id": 1,
          "name": "سورة السجدة الايات من 11 الى 30",
          "url": "https://server17.mp3quran.net/tafseer/tabri/032-11-30.mp3",
          "sura_id": 32
        },
        {
          "id": 188,
          "tafsir_id": 1,
          "name": "سورة الأحزاب الايات من 1 الى 17",
          "url": "https://server17.mp3quran.net/tafseer/tabri/033-1-17.mp3",
          "sura_id": 33
        },
        {
          "id": 189,
          "tafsir_id": 1,
          "name": "سورة الأحزاب الايات من 18 الى 30",
          "url": "https://server17.mp3quran.net/tafseer/tabri/033-18-30.mp3",
          "sura_id": 33
        },
        {
          "id": 190,
          "tafsir_id": 1,
          "name": "سورة الأحزاب الايات من 31 الى 50",
          "url": "https://server17.mp3quran.net/tafseer/tabri/033-31-50.mp3",
          "sura_id": 33
        },
        {
          "id": 191,
          "tafsir_id": 1,
          "name": "سورة الأحزاب الايات من 51 الى 59",
          "url": "https://server17.mp3quran.net/tafseer/tabri/033-51-59.mp3",
          "sura_id": 33
        },
        {
          "id": 192,
          "tafsir_id": 1,
          "name": "سورة الأحزاب الايات من 60 الى 73",
          "url": "https://server17.mp3quran.net/tafseer/tabri/033-60-73.mp3",
          "sura_id": 33
        },
        {
          "id": 193,
          "tafsir_id": 1,
          "name": "سورة سبأ الايات من 1 الى 9",
          "url": "https://server17.mp3quran.net/tafseer/tabri/034-1-9.mp3",
          "sura_id": 34
        },
        {
          "id": 194,
          "tafsir_id": 1,
          "name": "سورة سبأ الايات من 10 الى 23",
          "url": "https://server17.mp3quran.net/tafseer/tabri/034-10-23.mp3",
          "sura_id": 34
        },
        {
          "id": 195,
          "tafsir_id": 1,
          "name": "سورة سبأ الايات من 24 الى 45",
          "url": "https://server17.mp3quran.net/tafseer/tabri/034-24-45.mp3",
          "sura_id": 34
        },
        {
          "id": 196,
          "tafsir_id": 1,
          "name": "سورة سبأ الايات من 46 الى 54",
          "url": "https://server17.mp3quran.net/tafseer/tabri/034-46-54.mp3",
          "sura_id": 34
        },
        {
          "id": 197,
          "tafsir_id": 1,
          "name": "سورة فاطر الايات من 1 الى 14",
          "url": "https://server17.mp3quran.net/tafseer/tabri/035-1-14.mp3",
          "sura_id": 35
        },
        {
          "id": 198,
          "tafsir_id": 1,
          "name": "سورة فاطر الايات من 15 الى 40",
          "url": "https://server17.mp3quran.net/tafseer/tabri/035-15-40.mp3",
          "sura_id": 35
        },
        {
          "id": 199,
          "tafsir_id": 1,
          "name": "سورة فاطر الايات من 41 الى 45",
          "url": "https://server17.mp3quran.net/tafseer/tabri/035-41-45.mp3",
          "sura_id": 35
        },
        {
          "id": 200,
          "tafsir_id": 1,
          "name": "سورة يس الايات من 1 الى 27",
          "url": "https://server17.mp3quran.net/tafseer/tabri/036-1-27.mp3",
          "sura_id": 36
        },
        {
          "id": 201,
          "tafsir_id": 1,
          "name": "سورة يس الايات من 28 الى 59",
          "url": "https://server17.mp3quran.net/tafseer/tabri/036-28-59.mp3",
          "sura_id": 36
        },
        {
          "id": 202,
          "tafsir_id": 1,
          "name": "سورة يس الايات من 60 الى 83",
          "url": "https://server17.mp3quran.net/tafseer/tabri/036-60-83.mp3",
          "sura_id": 36
        },
        {
          "id": 203,
          "tafsir_id": 1,
          "name": "سورة الصافات الايات من 1 الى 21",
          "url": "https://server17.mp3quran.net/tafseer/tabri/037-1-21.mp3",
          "sura_id": 37
        },
        {
          "id": 204,
          "tafsir_id": 1,
          "name": "سورة الصافات الايات من 22 الى 82",
          "url": "https://server17.mp3quran.net/tafseer/tabri/037-22-82.mp3",
          "sura_id": 37
        },
        {
          "id": 205,
          "tafsir_id": 1,
          "name": "سورة الصافات الايات من 83 الى 144",
          "url": "https://server17.mp3quran.net/tafseer/tabri/037-83-144.mp3",
          "sura_id": 37
        },
        {
          "id": 206,
          "tafsir_id": 1,
          "name": "سورة الصافات الايات من 145 الى 182",
          "url": "https://server17.mp3quran.net/tafseer/tabri/037-145-182.mp3",
          "sura_id": 37
        },
        {
          "id": 207,
          "tafsir_id": 1,
          "name": "سورة ص الايات من 1 الى 20",
          "url": "https://server17.mp3quran.net/tafseer/tabri/038-1-20.mp3",
          "sura_id": 38
        },
        {
          "id": 208,
          "tafsir_id": 1,
          "name": "سورة ص الايات من 21 الى 51",
          "url": "https://server17.mp3quran.net/tafseer/tabri/038-21-51.mp3",
          "sura_id": 38
        },
        {
          "id": 209,
          "tafsir_id": 1,
          "name": "سورة ص الايات من 52 الى 88",
          "url": "https://server17.mp3quran.net/tafseer/tabri/038-52-88.mp3",
          "sura_id": 38
        },
        {
          "id": 210,
          "tafsir_id": 1,
          "name": "سورة الزمر الايات من 1 الى 7",
          "url": "https://server17.mp3quran.net/tafseer/tabri/039-1-7.mp3",
          "sura_id": 39
        },
        {
          "id": 211,
          "tafsir_id": 1,
          "name": "سورة الزمر الايات من 8 الى 31",
          "url": "https://server17.mp3quran.net/tafseer/tabri/039-8-31.mp3",
          "sura_id": 39
        },
        {
          "id": 212,
          "tafsir_id": 1,
          "name": "سورة الزمر الايات من 32 الى 52",
          "url": "https://server17.mp3quran.net/tafseer/tabri/039-32-52.mp3",
          "sura_id": 39
        },
        {
          "id": 213,
          "tafsir_id": 1,
          "name": "سورة الزمر الايات من 53 الى 75",
          "url": "https://server17.mp3quran.net/tafseer/tabri/039-53-75.mp3",
          "sura_id": 39
        },
        {
          "id": 214,
          "tafsir_id": 1,
          "name": "سورة غافر الايات من 1 الى 20",
          "url": "https://server17.mp3quran.net/tafseer/tabri/040-1-20.mp3",
          "sura_id": 40
        },
        {
          "id": 215,
          "tafsir_id": 1,
          "name": "سورة غافر الايات من 21 الى 40",
          "url": "https://server17.mp3quran.net/tafseer/tabri/040-21-40.mp3",
          "sura_id": 40
        },
        {
          "id": 216,
          "tafsir_id": 1,
          "name": "سورة غافر الايات من 41 الى 65",
          "url": "https://server17.mp3quran.net/tafseer/tabri/040-41-65.mp3",
          "sura_id": 40
        },
        {
          "id": 217,
          "tafsir_id": 1,
          "name": "سورة غافر الايات من 66 الى 85",
          "url": "https://server17.mp3quran.net/tafseer/tabri/040-66-85.mp3",
          "sura_id": 40
        },
        {
          "id": 218,
          "tafsir_id": 1,
          "name": "سورة فصلت الايات من 1 الى 8",
          "url": "https://server17.mp3quran.net/tafseer/tabri/041-1-8.mp3",
          "sura_id": 41
        },
        {
          "id": 219,
          "tafsir_id": 1,
          "name": "سورة فصلت الايات من 9 الى 24",
          "url": "https://server17.mp3quran.net/tafseer/tabri/041-9-24.mp3",
          "sura_id": 41
        },
        {
          "id": 220,
          "tafsir_id": 1,
          "name": "سورة فصلت الايات من 25 الى 46",
          "url": "https://server17.mp3quran.net/tafseer/tabri/041-25-46.mp3",
          "sura_id": 41
        },
        {
          "id": 221,
          "tafsir_id": 1,
          "name": "سورة فصلت الايات من 47 الى 54",
          "url": "https://server17.mp3quran.net/tafseer/tabri/041-47-54.mp3",
          "sura_id": 41
        },
        {
          "id": 222,
          "tafsir_id": 1,
          "name": "سورة الشورى الايات من 1 الى 12",
          "url": "https://server17.mp3quran.net/tafseer/tabri/042-1-12.mp3",
          "sura_id": 42
        },
        {
          "id": 223,
          "tafsir_id": 1,
          "name": "سورة الشورى الايات من 13 الى 26",
          "url": "https://server17.mp3quran.net/tafseer/tabri/042-13-26.mp3",
          "sura_id": 42
        },
        {
          "id": 224,
          "tafsir_id": 1,
          "name": "سورة الشورى الايات من 27 الى 50",
          "url": "https://server17.mp3quran.net/tafseer/tabri/042-27-50.mp3",
          "sura_id": 42
        },
        {
          "id": 225,
          "tafsir_id": 1,
          "name": "سورة الشورى الايات من 51 الى 53",
          "url": "https://server17.mp3quran.net/tafseer/tabri/042-51-53.mp3",
          "sura_id": 42
        },
        {
          "id": 226,
          "tafsir_id": 1,
          "name": "سورة الزخرف الايات من 1 الى 23",
          "url": "https://server17.mp3quran.net/tafseer/tabri/043-1-23.mp3",
          "sura_id": 43
        },
        {
          "id": 227,
          "tafsir_id": 1,
          "name": "سورة الزخرف الايات من 24 الى 56",
          "url": "https://server17.mp3quran.net/tafseer/tabri/043-24-56.mp3",
          "sura_id": 43
        },
        {
          "id": 228,
          "tafsir_id": 1,
          "name": "سورة الزخرف الايات من 57 الى 89",
          "url": "https://server17.mp3quran.net/tafseer/tabri/043-57-89.mp3",
          "sura_id": 43
        },
        {
          "id": 229,
          "tafsir_id": 1,
          "name": "سورة الدّخان الايات من 1 الى 16",
          "url": "https://server17.mp3quran.net/tafseer/tabri/044-1-16.mp3",
          "sura_id": 44
        },
        {
          "id": 230,
          "tafsir_id": 1,
          "name": "سورة الدّخان الايات من 17 الى 59",
          "url": "https://server17.mp3quran.net/tafseer/tabri/044-17-59.mp3",
          "sura_id": 44
        },
        {
          "id": 231,
          "tafsir_id": 1,
          "name": "سورة الجاثية الايات من 1 الى 11",
          "url": "https://server17.mp3quran.net/tafseer/tabri/045-1-11.mp3",
          "sura_id": 45
        },
        {
          "id": 232,
          "tafsir_id": 1,
          "name": "سورة الجاثية الايات من 12 الى 37",
          "url": "https://server17.mp3quran.net/tafseer/tabri/045-12-37.mp3",
          "sura_id": 45
        },
        {
          "id": 233,
          "tafsir_id": 1,
          "name": "سورة الأحقاف الايات من 1 الى 20",
          "url": "https://server17.mp3quran.net/tafseer/tabri/046-1-20.mp3",
          "sura_id": 46
        },
        {
          "id": 234,
          "tafsir_id": 1,
          "name": "سورة الأحقاف الايات من 21 الى 35",
          "url": "https://server17.mp3quran.net/tafseer/tabri/046-21-35.mp3",
          "sura_id": 46
        },
        {
          "id": 235,
          "tafsir_id": 1,
          "name": "سورة محمد الايات من 1 الى 9",
          "url": "https://server17.mp3quran.net/tafseer/tabri/047-1-9.mp3",
          "sura_id": 47
        },
        {
          "id": 236,
          "tafsir_id": 1,
          "name": "سورة محمد الايات من 10 الى 32",
          "url": "https://server17.mp3quran.net/tafseer/tabri/047-10-32.mp3",
          "sura_id": 47
        },
        {
          "id": 237,
          "tafsir_id": 1,
          "name": "سورة محمد الايات من 33 الى 38",
          "url": "https://server17.mp3quran.net/tafseer/tabri/047-33-38.mp3",
          "sura_id": 47
        },
        {
          "id": 238,
          "tafsir_id": 1,
          "name": "سورة الفتح الايات من 1 الى 17",
          "url": "https://server17.mp3quran.net/tafseer/tabri/048-1-17.mp3",
          "sura_id": 48
        },
        {
          "id": 239,
          "tafsir_id": 1,
          "name": "سورة الفتح الايات من 18 الى 29",
          "url": "https://server17.mp3quran.net/tafseer/tabri/048-18-29.mp3",
          "sura_id": 48
        },
        {
          "id": 240,
          "tafsir_id": 1,
          "name": "سورة الحجرات الايات من 1 الى 13",
          "url": "https://server17.mp3quran.net/tafseer/tabri/049-1-13.mp3",
          "sura_id": 49
        },
        {
          "id": 241,
          "tafsir_id": 1,
          "name": "سورة الحجرات الايات من 14 الى 18",
          "url": "https://server17.mp3quran.net/tafseer/tabri/049-14-18.mp3",
          "sura_id": 49
        },
        {
          "id": 242,
          "tafsir_id": 1,
          "name": "سورة ق الايات من 1 الى 26",
          "url": "https://server17.mp3quran.net/tafseer/tabri/050-1-26.mp3",
          "sura_id": 50
        },
        {
          "id": 243,
          "tafsir_id": 1,
          "name": "سورة ق الايات من 27 الى 45",
          "url": "https://server17.mp3quran.net/tafseer/tabri/050-27-45.mp3",
          "sura_id": 50
        },
        {
          "id": 244,
          "tafsir_id": 1,
          "name": "سورة الذاريات الايات من 1 الى 30",
          "url": "https://server17.mp3quran.net/tafseer/tabri/051-1-30.mp3",
          "sura_id": 51
        },
        {
          "id": 245,
          "tafsir_id": 1,
          "name": "سورة الذاريات الايات من 31 الى 60",
          "url": "https://server17.mp3quran.net/tafseer/tabri/051-31-60.mp3",
          "sura_id": 51
        },
        {
          "id": 246,
          "tafsir_id": 1,
          "name": "سورة الطور الايات من 1 الى 23",
          "url": "https://server17.mp3quran.net/tafseer/tabri/052-1-23.mp3",
          "sura_id": 52
        },
        {
          "id": 247,
          "tafsir_id": 1,
          "name": "سورة الطور الايات من 24 الى 49",
          "url": "https://server17.mp3quran.net/tafseer/tabri/052-24-49.mp3",
          "sura_id": 52
        },
        {
          "id": 248,
          "tafsir_id": 1,
          "name": "سورة النجم الايات من 1 الى 25",
          "url": "https://server17.mp3quran.net/tafseer/tabri/053-1-25.mp3",
          "sura_id": 53
        },
        {
          "id": 249,
          "tafsir_id": 1,
          "name": "سورة النجم الايات من 26 الى 62",
          "url": "https://server17.mp3quran.net/tafseer/tabri/053-26-62.mp3",
          "sura_id": 53
        },
        {
          "id": 250,
          "tafsir_id": 1,
          "name": "سورة القمر الايات من 1 الى 8",
          "url": "https://server17.mp3quran.net/tafseer/tabri/054-1-8.mp3",
          "sura_id": 54
        },
        {
          "id": 251,
          "tafsir_id": 1,
          "name": "سورة القمر الايات من 9 الى 55",
          "url": "https://server17.mp3quran.net/tafseer/tabri/054-9-55.mp3",
          "sura_id": 54
        },
        {
          "id": 252,
          "tafsir_id": 1,
          "name": "سورة الرحمن كاملة",
          "url": "https://server17.mp3quran.net/tafseer/tabri/055.mp3",
          "sura_id": 55
        },
        {
          "id": 253,
          "tafsir_id": 1,
          "name": "سورة الواقعة الايات من 1 الى 74",
          "url": "https://server17.mp3quran.net/tafseer/tabri/056-1-74.mp3",
          "sura_id": 56
        },
        {
          "id": 254,
          "tafsir_id": 1,
          "name": "سورة الواقعة الايات من 75 الى 96",
          "url": "https://server17.mp3quran.net/tafseer/tabri/056-75-96.mp3",
          "sura_id": 56
        },
        {
          "id": 255,
          "tafsir_id": 1,
          "name": "سورة الحديد الايات من 1 الى 15",
          "url": "https://server17.mp3quran.net/tafseer/tabri/057-1-15.mp3",
          "sura_id": 57
        },
        {
          "id": 256,
          "tafsir_id": 1,
          "name": "سورة الحديد الايات من 16 الى 29",
          "url": "https://server17.mp3quran.net/tafseer/tabri/057-16-29.mp3",
          "sura_id": 57
        },
        {
          "id": 257,
          "tafsir_id": 1,
          "name": "سورة المجادلة الايات من 1 الى 13",
          "url": "https://server17.mp3quran.net/tafseer/tabri/058-1-13.mp3",
          "sura_id": 58
        },
        {
          "id": 258,
          "tafsir_id": 1,
          "name": "سورة المجادلة الايات من 14 الى 22",
          "url": "https://server17.mp3quran.net/tafseer/tabri/058-14-22.mp3",
          "sura_id": 58
        },
        {
          "id": 259,
          "tafsir_id": 1,
          "name": "سورة الحشر الايات من 1 الى 10",
          "url": "https://server17.mp3quran.net/tafseer/tabri/059-1-10.mp3",
          "sura_id": 59
        },
        {
          "id": 260,
          "tafsir_id": 1,
          "name": "سورة الحشر الايات من 11 الى 24",
          "url": "https://server17.mp3quran.net/tafseer/tabri/059-11-24.mp3",
          "sura_id": 59
        },
        {
          "id": 261,
          "tafsir_id": 1,
          "name": "سورة الممتحنة الايات من 1 الى 6",
          "url": "https://server17.mp3quran.net/tafseer/tabri/060-1-6.mp3",
          "sura_id": 60
        },
        {
          "id": 262,
          "tafsir_id": 1,
          "name": "سورة الممتحنة الايات من 7 الى 13",
          "url": "https://server17.mp3quran.net/tafseer/tabri/060-7-13.mp3",
          "sura_id": 60
        },
        {
          "id": 263,
          "tafsir_id": 1,
          "name": "سورة الصف كاملة",
          "url": "https://server17.mp3quran.net/tafseer/tabri/061.mp3",
          "sura_id": 61
        },
        {
          "id": 264,
          "tafsir_id": 1,
          "name": "سورة الجمعة كاملة",
          "url": "https://server17.mp3quran.net/tafseer/tabri/062.mp3",
          "sura_id": 62
        },
        {
          "id": 265,
          "tafsir_id": 1,
          "name": "سورة المنافقون كاملة",
          "url": "https://server17.mp3quran.net/tafseer/tabri/063.mp3",
          "sura_id": 63
        },
        {
          "id": 266,
          "tafsir_id": 1,
          "name": "سورة التغابن كاملة",
          "url": "https://server17.mp3quran.net/tafseer/tabri/064.mp3",
          "sura_id": 64
        },
        {
          "id": 267,
          "tafsir_id": 1,
          "name": "سورة الطلاق كاملة",
          "url": "https://server17.mp3quran.net/tafseer/tabri/065.mp3",
          "sura_id": 65
        },
        {
          "id": 268,
          "tafsir_id": 1,
          "name": "سورة التحريم كاملة",
          "url": "https://server17.mp3quran.net/tafseer/tabri/066.mp3",
          "sura_id": 66
        },
        {
          "id": 269,
          "tafsir_id": 1,
          "name": "سورة الملك كاملة",
          "url": "https://server17.mp3quran.net/tafseer/tabri/067.mp3",
          "sura_id": 67
        },
        {
          "id": 270,
          "tafsir_id": 1,
          "name": "سورة القلم كاملة",
          "url": "https://server17.mp3quran.net/tafseer/tabri/068.mp3",
          "sura_id": 68
        },
        {
          "id": 271,
          "tafsir_id": 1,
          "name": "سورة الحاقة كاملة",
          "url": "https://server17.mp3quran.net/tafseer/tabri/069.mp3",
          "sura_id": 69
        },
        {
          "id": 272,
          "tafsir_id": 1,
          "name": "سورة المعارج كاملة",
          "url": "https://server17.mp3quran.net/tafseer/tabri/070.mp3",
          "sura_id": 70
        },
        {
          "id": 273,
          "tafsir_id": 1,
          "name": "سورة نوح كاملة",
          "url": "https://server17.mp3quran.net/tafseer/tabri/071.mp3",
          "sura_id": 71
        },
        {
          "id": 274,
          "tafsir_id": 1,
          "name": "سورة الجن كاملة",
          "url": "https://server17.mp3quran.net/tafseer/tabri/072.mp3",
          "sura_id": 72
        },
        {
          "id": 275,
          "tafsir_id": 1,
          "name": "سورة المزمل كاملة",
          "url": "https://server17.mp3quran.net/tafseer/tabri/073.mp3",
          "sura_id": 73
        },
        {
          "id": 276,
          "tafsir_id": 1,
          "name": "سورة المدثر كاملة",
          "url": "https://server17.mp3quran.net/tafseer/tabri/074.mp3",
          "sura_id": 74
        },
        {
          "id": 277,
          "tafsir_id": 1,
          "name": "سورة القيامة كاملة",
          "url": "https://server17.mp3quran.net/tafseer/tabri/075.mp3",
          "sura_id": 75
        },
        {
          "id": 278,
          "tafsir_id": 1,
          "name": "سورة الإنسان كاملة",
          "url": "https://server17.mp3quran.net/tafseer/tabri/076.mp3",
          "sura_id": 76
        },
        {
          "id": 279,
          "tafsir_id": 1,
          "name": "سورة المرسلات كاملة",
          "url": "https://server17.mp3quran.net/tafseer/tabri/077.mp3",
          "sura_id": 77
        },
        {
          "id": 280,
          "tafsir_id": 1,
          "name": "سورة النبأ كاملة",
          "url": "https://server17.mp3quran.net/tafseer/tabri/078.mp3",
          "sura_id": 78
        },
        {
          "id": 281,
          "tafsir_id": 1,
          "name": "سورة النازعات كاملة",
          "url": "https://server17.mp3quran.net/tafseer/tabri/079.mp3",
          "sura_id": 79
        },
        {
          "id": 282,
          "tafsir_id": 1,
          "name": "سورة عبس كاملة",
          "url": "https://server17.mp3quran.net/tafseer/tabri/080.mp3",
          "sura_id": 80
        },
        {
          "id": 283,
          "tafsir_id": 1,
          "name": "سورة التكوير كاملة",
          "url": "https://server17.mp3quran.net/tafseer/tabri/081.mp3",
          "sura_id": 81
        },
        {
          "id": 284,
          "tafsir_id": 1,
          "name": "سورة الإنفطار كاملة",
          "url": "https://server17.mp3quran.net/tafseer/tabri/082.mp3",
          "sura_id": 82
        },
        {
          "id": 285,
          "tafsir_id": 1,
          "name": "سورة المطففين كاملة",
          "url": "https://server17.mp3quran.net/tafseer/tabri/083.mp3",
          "sura_id": 83
        },
        {
          "id": 286,
          "tafsir_id": 1,
          "name": "سورة الإنشقاق كاملة",
          "url": "https://server17.mp3quran.net/tafseer/tabri/084.mp3",
          "sura_id": 84
        },
        {
          "id": 287,
          "tafsir_id": 1,
          "name": "سورة البروج كاملة",
          "url": "https://server17.mp3quran.net/tafseer/tabri/085.mp3",
          "sura_id": 85
        },
        {
          "id": 288,
          "tafsir_id": 1,
          "name": "سورة الطارق كاملة",
          "url": "https://server17.mp3quran.net/tafseer/tabri/086.mp3",
          "sura_id": 86
        },
        {
          "id": 289,
          "tafsir_id": 1,
          "name": "سورة الأعلى كاملة",
          "url": "https://server17.mp3quran.net/tafseer/tabri/087.mp3",
          "sura_id": 87
        },
        {
          "id": 290,
          "tafsir_id": 1,
          "name": "سورة الغاشية كاملة",
          "url": "https://server17.mp3quran.net/tafseer/tabri/088.mp3",
          "sura_id": 88
        },
        {
          "id": 291,
          "tafsir_id": 1,
          "name": "سورة الفجر كاملة",
          "url": "https://server17.mp3quran.net/tafseer/tabri/089.mp3",
          "sura_id": 89
        },
        {
          "id": 292,
          "tafsir_id": 1,
          "name": "سورة البلد كاملة",
          "url": "https://server17.mp3quran.net/tafseer/tabri/090.mp3",
          "sura_id": 90
        },
        {
          "id": 293,
          "tafsir_id": 1,
          "name": "سورة الشمس كاملة",
          "url": "https://server17.mp3quran.net/tafseer/tabri/091.mp3",
          "sura_id": 91
        },
        {
          "id": 294,
          "tafsir_id": 1,
          "name": "سورة الليل كاملة",
          "url": "https://server17.mp3quran.net/tafseer/tabri/092.mp3",
          "sura_id": 92
        },
        {
          "id": 295,
          "tafsir_id": 1,
          "name": "سورة الضحى كاملة",
          "url": "https://server17.mp3quran.net/tafseer/tabri/093.mp3",
          "sura_id": 93
        },
        {
          "id": 296,
          "tafsir_id": 1,
          "name": "سورة الشرح كاملة",
          "url": "https://server17.mp3quran.net/tafseer/tabri/094.mp3",
          "sura_id": 94
        },
        {
          "id": 297,
          "tafsir_id": 1,
          "name": "سورة التين كاملة",
          "url": "https://server17.mp3quran.net/tafseer/tabri/095.mp3",
          "sura_id": 95
        },
        {
          "id": 298,
          "tafsir_id": 1,
          "name": "سورة العلق كاملة",
          "url": "https://server17.mp3quran.net/tafseer/tabri/096.mp3",
          "sura_id": 96
        },
        {
          "id": 299,
          "tafsir_id": 1,
          "name": "سورة القدر كاملة",
          "url": "https://server17.mp3quran.net/tafseer/tabri/097.mp3",
          "sura_id": 97
        },
        {
          "id": 300,
          "tafsir_id": 1,
          "name": "سورة البينة كاملة",
          "url": "https://server17.mp3quran.net/tafseer/tabri/098.mp3",
          "sura_id": 98
        },
        {
          "id": 301,
          "tafsir_id": 1,
          "name": "سورة الزلزلة كاملة",
          "url": "https://server17.mp3quran.net/tafseer/tabri/099.mp3",
          "sura_id": 99
        },
        {
          "id": 302,
          "tafsir_id": 1,
          "name": "سورة العاديات كاملة",
          "url": "https://server17.mp3quran.net/tafseer/tabri/100.mp3",
          "sura_id": 100
        },
        {
          "id": 303,
          "tafsir_id": 1,
          "name": "سورة القارعة كاملة",
          "url": "https://server17.mp3quran.net/tafseer/tabri/101.mp3",
          "sura_id": 101
        },
        {
          "id": 304,
          "tafsir_id": 1,
          "name": "سورة التكاثر كاملة",
          "url": "https://server17.mp3quran.net/tafseer/tabri/102.mp3",
          "sura_id": 102
        },
        {
          "id": 305,
          "tafsir_id": 1,
          "name": "سورة العصر كاملة",
          "url": "https://server17.mp3quran.net/tafseer/tabri/103.mp3",
          "sura_id": 103
        },
        {
          "id": 306,
          "tafsir_id": 1,
          "name": "سورة الهمزة كاملة",
          "url": "https://server17.mp3quran.net/tafseer/tabri/104.mp3",
          "sura_id": 104
        },
        {
          "id": 307,
          "tafsir_id": 1,
          "name": "سورة الفيل كاملة",
          "url": "https://server17.mp3quran.net/tafseer/tabri/105.mp3",
          "sura_id": 105
        },
        {
          "id": 308,
          "tafsir_id": 1,
          "name": "سورة قريش كاملة",
          "url": "https://server17.mp3quran.net/tafseer/tabri/106.mp3",
          "sura_id": 106
        },
        {
          "id": 309,
          "tafsir_id": 1,
          "name": "سورة الماعون كاملة",
          "url": "https://server17.mp3quran.net/tafseer/tabri/107.mp3",
          "sura_id": 107
        },
        {
          "id": 310,
          "tafsir_id": 1,
          "name": "سورة الكوثر كاملة",
          "url": "https://server17.mp3quran.net/tafseer/tabri/108.mp3",
          "sura_id": 108
        },
        {
          "id": 311,
          "tafsir_id": 1,
          "name": "سورة الكافرون كاملة",
          "url": "https://server17.mp3quran.net/tafseer/tabri/109.mp3",
          "sura_id": 109
        },
        {
          "id": 312,
          "tafsir_id": 1,
          "name": "سورة النصر كاملة",
          "url": "https://server17.mp3quran.net/tafseer/tabri/110.mp3",
          "sura_id": 110
        },
        {
          "id": 313,
          "tafsir_id": 1,
          "name": "سورة المسد كاملة",
          "url": "https://server17.mp3quran.net/tafseer/tabri/111.mp3",
          "sura_id": 111
        },
        {
          "id": 314,
          "tafsir_id": 1,
          "name": "سورة الإخلاص كاملة",
          "url": "https://server17.mp3quran.net/tafseer/tabri/112.mp3",
          "sura_id": 112
        },
        {
          "id": 315,
          "tafsir_id": 1,
          "name": "سورة الفلق كاملة",
          "url": "https://server17.mp3quran.net/tafseer/tabri/113.mp3",
          "sura_id": 113
        },
        {
          "id": 316,
          "tafsir_id": 1,
          "name": "سورة الناس كاملة",
          "url": "https://server17.mp3quran.net/tafseer/tabri/114.mp3",
          "sura_id": 114
        }
      ]
    }
  }
